cli_pets/__init__.py
cli_pets/constants.py
cli_pets/greet.py
cli_pets/py.typed
cli_pets/race.py
cli_pets/walk.py
cli_pets-0.1.1.dist-info/WHEEL
cli_pets-0.1.1.dist-info/METADATA
cli_pets-0.1.1.dist-info/RECORD
