Metadata-Version: 2.4
Name: cli-pets
Version: 0.1.1
Summary: Interactive CLI pets with animated emoji characters for your terminal
Keywords: cli,terminal,animation,emoji,pets,fun
Author: Ran Li
Author-email: Ran Li <ranli2011@gmail.com>
License-Expression: MIT
Classifier: Development Status :: 3 - Alpha
Classifier: Intended Audience :: Developers
Classifier: License :: OSI Approved :: MIT License
Classifier: Programming Language :: Python :: 3
Classifier: Programming Language :: Python :: 3.12
Classifier: Topic :: Utilities
Classifier: Environment :: Console
Requires-Dist: rich>=14.2.0
Requires-Python: >=3.12
Project-URL: Homepage, https://github.com/ran-codes/cli-pets
Project-URL: Issues, https://github.com/ran-codes/cli-pets/issues
Project-URL: Repository, https://github.com/ran-codes/cli-pets
